ewoksdask/__init__.py
ewoksdask/__main__.py
ewoksdask/bindings.py
ewoksdask/engine.py
ewoksdask/schedulers.py
ewoksdask/tests/__init__.py
ewoksdask/tests/conftest.py
ewoksdask/tests/test_examples.py
ewoksdask/tests/test_workflow_events.py
ewoksdask-2.0.1.dist-info/licenses/LICENSE.md
ewoksdask-2.0.1.dist-info/METADATA
ewoksdask-2.0.1.dist-info/WHEEL
ewoksdask-2.0.1.dist-info/entry_points.txt
ewoksdask-2.0.1.dist-info/top_level.txt
ewoksdask-2.0.1.dist-info/RECORD
