Metadata-Version: 2.4
Name: ewoksdask
Version: 2.0.1
Summary: Dask binding for Ewoks
Author-email: ESRF <dau-pydev@esrf.fr>
License: # MIT License
Project-URL: Homepage, https://gitlab.esrf.fr/workflow/ewoks/ewoksdask/
Project-URL: Documentation, https://ewoksdask.readthedocs.io/
Project-URL: Repository, https://gitlab.esrf.fr/workflow/ewoks/ewoksdask/
Project-URL: Issues, https://gitlab.esrf.fr/workflow/ewoks/ewoksdask/issues
Project-URL: Changelog, https://gitlab.esrf.fr/workflow/ewoks/ewoksdask/-/blob/main/CHANGELOG.md
Classifier: Intended Audience :: Science/Research
Classifier: License :: OSI Approved :: MIT License
Classifier: Programming Language :: Python :: 3
Requires-Python: >=3.8
License-File: LICENSE.md
Requires-Dist: ewokscore>=4.0.1
Requires-Dist: dask[distributed]>=2021.3.0
Requires-Dist: dask-jobqueue>=0.7.3
Requires-Dist: sphinx-argparse
Requires-Dist: sphinx-copybutton
Provides-Extra: dashboard
Requires-Dist: dask[diagnostics]>=2021.3.0; extra == "dashboard"
Provides-Extra: test
Requires-Dist: pytest>=7; extra == "test"
Provides-Extra: dev
Requires-Dist: ewoksdask[test]; extra == "dev"
Requires-Dist: black>=25; extra == "dev"
Requires-Dist: flake8>=4; extra == "dev"
Requires-Dist: isort; extra == "dev"
Provides-Extra: doc
Requires-Dist: ewoksdask[test]; extra == "doc"
Requires-Dist: sphinx>=4.5; extra == "doc"
Requires-Dist: sphinx-autodoc-typehints>=1.16; extra == "doc"
Requires-Dist: pydata-sphinx-theme; extra == "doc"
Dynamic: license-file
